LICENSE
README.md
setup.py
filecachetools/__init__.py
filecachetools.egg-info/PKG-INFO
filecachetools.egg-info/SOURCES.txt
filecachetools.egg-info/dependency_links.txt
filecachetools.egg-info/requires.txt
filecachetools.egg-info/top_level.txt