Metadata-Version: 2.1
Name: filecachetools
Version: 2.1.0
Summary: Rocket.Chat.Audit package takeover by Roland Hack, Proof of Concept for educational and ethical usage only.
Author: Chocapikk
Classifier: Development Status :: 3 - Alpha
Classifier: Intended Audience :: Developers
Classifier: Natural Language :: English
Classifier: Programming Language :: Python :: 3
Classifier: Programming Language :: Python :: 3.8
Classifier: Programming Language :: Python :: 3.9
Classifier: License :: OSI Approved :: MIT License
Classifier: Operating System :: OS Independent
Requires-Python: >=3.6
License-File: LICENSE
